pdfminer_cython/__init__.py
pdfminer_cython/arcfour.so
pdfminer_cython/ascii85.so
pdfminer_cython/ccitt.so
pdfminer_cython/cmapdb.so
pdfminer_cython/converter.so
pdfminer_cython/encodingdb.so
pdfminer_cython/fontmetrics.so
pdfminer_cython/glyphlist.so
pdfminer_cython/image.so
pdfminer_cython/latin_enc.so
pdfminer_cython/layout.so
pdfminer_cython/lzw.so
pdfminer_cython/pdfcolor.so
pdfminer_cython/pdfdevice.so
pdfminer_cython/pdfdocument.so
pdfminer_cython/pdffont.so
pdfminer_cython/pdfinterp.so
pdfminer_cython/pdfpage.so
pdfminer_cython/pdfparser.so
pdfminer_cython/pdftypes.so
pdfminer_cython/psparser.so
pdfminer_cython/rijndael.so
pdfminer_cython/runlength.so
pdfminer_cython/utils.so
pdfminer_cython/cmap/78-EUC-H.pickle.gz
pdfminer_cython/cmap/78-EUC-V.pickle.gz
pdfminer_cython/cmap/78-H.pickle.gz
pdfminer_cython/cmap/78-RKSJ-H.pickle.gz
pdfminer_cython/cmap/78-RKSJ-V.pickle.gz
pdfminer_cython/cmap/78-V.pickle.gz
pdfminer_cython/cmap/78ms-RKSJ-H.pickle.gz
pdfminer_cython/cmap/78ms-RKSJ-V.pickle.gz
pdfminer_cython/cmap/83pv-RKSJ-H.pickle.gz
pdfminer_cython/cmap/83pv-RKSJ-V.pickle.gz
pdfminer_cython/cmap/90ms-RKSJ-H.pickle.gz
pdfminer_cython/cmap/90ms-RKSJ-V.pickle.gz
pdfminer_cython/cmap/90msp-RKSJ-H.pickle.gz
pdfminer_cython/cmap/90msp-RKSJ-V.pickle.gz
pdfminer_cython/cmap/90pv-RKSJ-H.pickle.gz
pdfminer_cython/cmap/90pv-RKSJ-V.pickle.gz
pdfminer_cython/cmap/Add-H.pickle.gz
pdfminer_cython/cmap/Add-RKSJ-H.pickle.gz
pdfminer_cython/cmap/Add-RKSJ-V.pickle.gz
pdfminer_cython/cmap/Add-V.pickle.gz
pdfminer_cython/cmap/B5-H.pickle.gz
pdfminer_cython/cmap/B5-V.pickle.gz
pdfminer_cython/cmap/B5pc-H.pickle.gz
pdfminer_cython/cmap/B5pc-V.pickle.gz
pdfminer_cython/cmap/CNS-EUC-H.pickle.gz
pdfminer_cython/cmap/CNS-EUC-V.pickle.gz
pdfminer_cython/cmap/CNS1-H.pickle.gz
pdfminer_cython/cmap/CNS1-V.pickle.gz
pdfminer_cython/cmap/CNS2-H.pickle.gz
pdfminer_cython/cmap/CNS2-V.pickle.gz
pdfminer_cython/cmap/ETHK-B5-H.pickle.gz
pdfminer_cython/cmap/ETHK-B5-V.pickle.gz
pdfminer_cython-20200304.dist-info/METADATA
pdfminer_cython-20200304.dist-info/WHEEL
pdfminer_cython-20200304.dist-info/top_level.txt
pdfminer_cython-20200304.dist-info/RECORD
