Metadata-Version: 2.1
Name: pdfminer-cython
Version: 20200304
Summary: PDF parser and analyzer
Home-page: http://euske.github.io/pdfminer/index.html
Author: Yusuke Shinyama, Franciszek Piszcz
Author-email: yusuke@cs.nyu.edu
License: MIT/X
Keywords: pdf parser,pdf converter,layout analysis,text mining
Platform: UNKNOWN
Classifier: Development Status :: 4 - Beta
Classifier: Environment :: Console
Classifier: Intended Audience :: Developers
Classifier: Intended Audience :: Science/Research
Classifier: License :: OSI Approved :: MIT License
Classifier: Topic :: Text Processing
